{
  "capital_france": {
    "topic": "capitals",
    "question_text": "What is the capital of France?",
    "answers": [
      {
        "text": "Paris",
        "correct": true,
        "response": "Correct! Paris is the capital and largest city of France, known for the Eiffel Tower.",
        "reward_knowledge": "European Capitals"
      },
      {
        "text": "Lyon",
        "correct": false,
        "response": "Incorrect. Lyon is France's third-largest city. The capital is Paris."
      },
      {
        "text": "Marseille",
        "correct": false,
        "response": "Incorrect. Marseille is France's second-largest city. The capital is Paris."
      },
      {
        "text": "Nice",
        "correct": false,
        "response": "Incorrect. Nice is on the French Riviera. The capital is Paris."
      }
    ]
  },
  "longest_river": {
    "topic": "physical_geography",
    "question_text": "What is the longest river in the world?",
    "answers": [
      {
        "text": "Nile River (Africa)",
        "correct": true,
        "response": "Correct! The Nile is approximately 6,650 km long, flowing through northeastern Africa.",
        "reward_knowledge": "World Rivers"
      },
      {
        "text": "Amazon River (South America)",
        "correct": false,
        "response": "Close! The Amazon is the second longest but carries the most water. The Nile is longest."
      },
      {
        "text": "Mississippi River (North America)",
        "correct": false,
        "response": "Incorrect. The Mississippi is one of North America's major rivers, but the Nile is longest."
      },
      {
        "text": "Yangtze River (Asia)",
        "correct": false,
        "response": "Incorrect. The Yangtze is Asia's longest river, but the Nile is the world's longest."
      }
    ]
  },
  "highest_mountain": {
    "topic": "physical_geography",
    "question_text": "What is the highest mountain peak in the world?",
    "answers": [
      {
        "text": "Mount Everest",
        "correct": true,
        "response": "Correct! Mount Everest, in the Himalayas, is Earth's highest mountain above sea level at 8,849m.",
        "reward_knowledge": "Mountain Systems"
      },
      {
        "text": "K2",
        "correct": false,
        "response": "Incorrect. K2 is the second highest peak. Mount Everest is the highest."
      },
      {
        "text": "Kilimanjaro",
        "correct": false,
        "response": "Incorrect. Kilimanjaro is Africa's highest peak. Mount Everest is the world's highest."
      },
      {
        "text": "Denali",
        "correct": false,
        "response": "Incorrect. Denali is North America's highest peak. Mount Everest is the world's highest."
      }
    ]
  },
  "country_australia": {
    "topic": "countries",
    "question_text": "Which continent is also a country?",
    "answers": [
      {
        "text": "Australia",
        "correct": true,
        "response": "Correct! Australia is both a country and a continent, the world's smallest continent.",
        "reward_knowledge": "Continents and Countries"
      },
      {
        "text": "Antarctica",
        "correct": false,
        "response": "Incorrect. Antarctica is a continent but not a country. Australia is both."
      },
      {
        "text": "Greenland",
        "correct": false,
        "response": "Incorrect. Greenland is a large island but not a continent. Australia is both a continent and country."
      },
      {
        "text": "Asia",
        "correct": false,
        "response": "Incorrect. Asia is a continent containing many countries. Australia is both a continent and country."
      }
    ]
  },
  "largest_desert": {
    "topic": "physical_geography",
    "question_text": "What is the largest hot desert in the world?",
    "answers": [
      {
        "text": "Sahara Desert",
        "correct": true,
        "response": "Correct! The Sahara covers about 9 million km² across North Africa.",
        "reward_knowledge": "Desert Geography"
      },
      {
        "text": "Gobi Desert",
        "correct": false,
        "response": "Incorrect. The Gobi is in Asia and much smaller. The Sahara is the largest hot desert."
      },
      {
        "text": "Kalahari Desert",
        "correct": false,
        "response": "Incorrect. The Kalahari is in southern Africa and smaller. The Sahara is the largest hot desert."
      },
      {
        "text": "Arabian Desert",
        "correct": false,
        "response": "Incorrect. The Arabian Desert is large but smaller than the Sahara."
      }
    ]
  },
  "ocean_largest": {
    "topic": "physical_geography",
    "question_text": "What is the largest ocean on Earth?",
    "answers": [
      {
        "text": "Pacific Ocean",
        "correct": true,
        "response": "Correct! The Pacific Ocean covers about 165 million km², nearly half of Earth's water surface.",
        "reward_knowledge": "Ocean Systems"
      },
      {
        "text": "Atlantic Ocean",
        "correct": false,
        "response": "Incorrect. The Atlantic is the second largest ocean. The Pacific is the largest."
      },
      {
        "text": "Indian Ocean",
        "correct": false,
        "response": "Incorrect. The Indian Ocean is the third largest. The Pacific is the largest."
      },
      {
        "text": "Arctic Ocean",
        "correct": false,
        "response": "Incorrect. The Arctic is the smallest ocean. The Pacific is the largest."
      }
    ]
  }
}
